<?xml version="1.0"?>
<!DOCTYPE hibernate-mapping PUBLIC
        "-//Hibernate/Hibernate Mapping DTD 3.0//EN"
        "http://www.hibernate.org/dtd/hibernate-mapping-3.0.dtd">

<hibernate-mapping package="Fuli">
	<class name="W_SQL_AIP" table="Fuli_User_AIP">
		<id name="CS" column="CS"></id>
		<property name="a" column="a"></property>
		<property name="x" column="x"></property>
		<property name="n" column="n"></property>
		<property name="M" column="M"></property>
	</class>
</hibernate-mapping>